README.rst
setup.py
spynach_ming/__init__.py
spynach_ming.egg-info/PKG-INFO
spynach_ming.egg-info/SOURCES.txt
spynach_ming.egg-info/dependency_links.txt
spynach_ming.egg-info/entry_points.txt
spynach_ming.egg-info/not-zip-safe
spynach_ming.egg-info/requires.txt
spynach_ming.egg-info/top_level.txt