Metadata-Version: 1.0
Name: spynach-ming
Version: 0.1
Summary: Ming MongoDB ODM plugin for Spynach web framework
Home-page: http://simock85.github.com/spynach.ming/
Author: Simone Marzola
Author-email: marzolasimone@gmail.com
License: GPL
Keywords: spynach mongodb ming odm
Platform: UNKNOWN
Classifier: Development Status :: 5 - Production/Stable
Classifier: License :: OSI Approved :: GNU General Public License (GPL)
Classifier: Environment :: Web Environment
